ascii_monet/__init__.py
ascii_monet/ascii_monet.py
ascii_monet/cli.py
ascii_monet/assets/darkside.jpg
ascii_monet/assets/earth.jpg
ascii_monet/assets/flowers.jpg
ascii_monet/assets/mushrooms.webp
ascii_monet/assets/mushrooms_red.jpg
ascii_monet/assets/pearl.png
ascii_monet/assets/fonts/CascadiaMono-Regular.otf
ascii_monet-0.0.6.dist-info/METADATA
ascii_monet-0.0.6.dist-info/WHEEL
ascii_monet-0.0.6.dist-info/entry_points.txt
ascii_monet-0.0.6.dist-info/licenses/LICENSE
ascii_monet-0.0.6.dist-info/RECORD
